reeco/__init__.py
reeco/__main__.py
reeco/schema.py
reeco/validator.py
reeco/schema/component.yml
reeco/schema/container.yml
reeco/schema/licences.yml
reeco/schema/schema.yml
reeco-0.0.2.post1707846505.dist-info/LICENSE
reeco-0.0.2.post1707846505.dist-info/WHEEL
reeco-0.0.2.post1707846505.dist-info/METADATA
reeco-0.0.2.post1707846505.dist-info/RECORD
